module_qc_tools/__init__.py
module_qc_tools/_version.py
module_qc_tools/console.py
module_qc_tools/typing_compat.py
module_qc_tools/cli/ADC_CALIBRATION.py
module_qc_tools/cli/ANALOG_READBACK.py
module_qc_tools/cli/DATA_TRANSMISSION.py
module_qc_tools/cli/INJECTION_CAPACITANCE.py
module_qc_tools/cli/IV_MEASURE.py
module_qc_tools/cli/LONG_TERM_STABILITY_DCS.py
module_qc_tools/cli/LP_MODE.py
module_qc_tools/cli/OVERVOLTAGE_PROTECTION.py
module_qc_tools/cli/SLDO.py
module_qc_tools/cli/UNDERSHUNT_PROTECTION.py
module_qc_tools/cli/VCAL_CALIBRATION.py
module_qc_tools/cli/__init__.py
module_qc_tools/cli/__main__.py
module_qc_tools/cli/get_nominal_current.py
module_qc_tools/cli/globals.py
module_qc_tools/cli/hardware_emulator.py
module_qc_tools/cli/main.py
module_qc_tools/cli/split_old_config.py
module_qc_tools/cli/upload_localdb.py
module_qc_tools/cli/yarr.py
module_qc_tools/data/configs/hw_config_emulator_merged_vmux.json
module_qc_tools/data/configs/hw_config_example_felix_merged_vmux_itkpixv2.json
module_qc_tools/data/configs/hw_config_example_felix_merged_vmux_v1.json
module_qc_tools/data/configs/hw_config_example_felix_separate_vmux_itkpixv2.json
module_qc_tools/data/configs/hw_config_example_felix_separate_vmux_v1.json
module_qc_tools/data/configs/hw_config_example_merged_vmux_itkpixv2.json
module_qc_tools/data/configs/hw_config_example_merged_vmux_v1.json
module_qc_tools/data/configs/hw_config_example_separate_vmux_itkpixv2.json
module_qc_tools/data/configs/hw_config_example_separate_vmux_v1.json
module_qc_tools/data/configs/meas_config.json
module_qc_tools/data/emulator/module_state_template.json
module_qc_tools/data/emulator/configs/connectivity/20UPGXM1234567_Lx_dummy.json
module_qc_tools/data/emulator/configs/connectivity/20UPGXM1234567_Lx_dummy_disabledchip.json
module_qc_tools/data/emulator/configs/connectivity/20UPGXM1234567_info.json
module_qc_tools/data/emulator/configs/connectivity/chip/dummy_chip1.json
module_qc_tools-2.6.0.dist-info/METADATA
module_qc_tools-2.6.0.dist-info/WHEEL
module_qc_tools-2.6.0.dist-info/entry_points.txt
module_qc_tools-2.6.0.dist-info/licenses/LICENSE
module_qc_tools-2.6.0.dist-info/RECORD
