Metadata-Version: 2.4
Name: module_qc_tools
Version: 2.6.0
Summary: Module qc tools
Project-URL: Homepage, https://gitlab.cern.ch/atlas-itk/pixel/module/module-qc-tools
Project-URL: Bug Tracker, https://gitlab.cern.ch/atlas-itk/pixel/module/module-qc-tools/-/issues
Project-URL: Source, https://gitlab.cern.ch/atlas-itk/pixel/module/module-qc-tools
Project-URL: Documentation, https://atlas-itk-pixel-mqt.docs.cern.ch/2.6/
Author-email: Jay Chan <jay.chan@cern.ch>
Maintainer-email: Giordon Stark <gstark@cern.ch>
License: Copyright (c) 2018 ATLAS ITk Pixel Modules
License-File: LICENSE
Classifier: License :: OSI Approved :: MIT License
Classifier: Operating System :: OS Independent
Classifier: Programming Language :: Python :: 3
Requires-Python: >=3.9
Requires-Dist: check-jsonschema
Requires-Dist: module-qc-data-tools>=1.3.0
Requires-Dist: module-qc-database-tools>=2.7.0
Requires-Dist: numpy
Requires-Dist: packaging
Requires-Dist: pre-commit
Requires-Dist: requests
Requires-Dist: rich
Requires-Dist: tabulate
Requires-Dist: typer>=0.9.0
Requires-Dist: urllib3<2,>=1.26.20; 'el7.x86_64' in platform_release
